django_ctct/__init__.py
django_ctct/admin.py
django_ctct/apps.py
django_ctct/management/commands/import_ctct.py
django_ctct/managers.py
django_ctct/migrations/0001_initial.py
django_ctct/migrations/__init__.py
django_ctct/models.py
django_ctct/signals.py
django_ctct/urls.py
django_ctct/utils.py
django_ctct/vendor.py
django_ctct/views.py
django_ctct-0.0.1.dev5.dist-info/METADATA
django_ctct-0.0.1.dev5.dist-info/WHEEL
django_ctct-0.0.1.dev5.dist-info/licenses/LICENSE
django_ctct-0.0.1.dev5.dist-info/RECORD
