Metadata-Version: 2.4
Name: django-ctct
Version: 0.0.1.dev5
Summary: A Django interface for the Constant Contact API
License: MIT
License-File: LICENSE
Author: Geoffrey Eisenbarth
Author-email: geoffrey.eisenbarth@gmail.com
Requires-Python: >=3.10
Classifier: License :: OSI Approved :: MIT License
Classifier: Programming Language :: Python :: 3
Classifier: Programming Language :: Python :: 3.10
Classifier: Programming Language :: Python :: 3.11
Classifier: Programming Language :: Python :: 3.12
Classifier: Programming Language :: Python :: 3.13
Classifier: Programming Language :: Python :: 3.14
Requires-Dist: django (>=3.2.0,<6.0.0)
Requires-Dist: mypy (>=1.19.0,<2.0.0)
Requires-Dist: pyjwt[crypto] (>=2.10.1,<3.0.0)
Requires-Dist: ratelimit (>=2.2.1,<3.0.0)
Requires-Dist: requests (>=2.32.3,<3.0.0)
Requires-Dist: tqdm (>=4.67.1,<5.0.0)
